{
  "last_updated": "2025-08-14T17:24:05.305037",
  "transactions": [
    {
      "date": "2025-08-14",
      "team": "Milwaukee Brewers",
      "details": "Milwaukee Brewerssent LFJake Bauerson a rehab assignment to Nashville Sounds.",
      "player": "Jake Bauers"
    },
    {
      "date": "2025-08-14",
      "team": "Atlanta Braves",
      "details": "Atlanta Bravesdesignated RHPCarlos Carrascofor assignment.",
      "player": "Carlos Carrasco"
    },
    {
      "date": "2025-08-14",
      "team": "Atlanta Braves",
      "details": "Atlanta Bravesrecalled RHPHunter Strattonfrom Gwinnett Stripers.",
      "player": "Hunter Stratton"
    }
  ]
}