{
  "last_updated": "2025-07-18T14:27:17.888502",
  "transactions": [
    {
      "date": "2025-07-18",
      "team": "Minnesota Twins",
      "details": "Minnesota Twinssent RHPBailey Oberon a rehab assignment to St. Paul Saints.",
      "player": "Bailey Ober"
    },
    {
      "date": "2025-07-18",
      "team": "Minnesota Twins",
      "details": "Minnesota Twinssent 2BLuke Keaschallon a rehab assignment to St. Paul Saints.",
      "player": "Luke Keaschall"
    },
    {
      "date": "2025-07-18",
      "team": "Atlanta Braves",
      "details": "Atlanta Bravesactivated RHPDane Dunning.",
      "player": "Dane Dunning"
    },
    {
      "date": "2025-07-18",
      "team": "Texas Rangers",
      "details": "Texas Rangerstraded RHPDane DunningtoAtlanta Bravesfor RHP José Ruiz and cash.",
      "player": "Dane Dunning"
    },
    {
      "date": "2025-07-18",
      "team": "Texas Rangers",
      "details": "Texas Rangerstraded RHP Dane Dunning toAtlanta Bravesfor RHPJosé Ruizand cash.",
      "player": "José Ruiz"
    }
  ]
}