{
  "last_updated": "2025-09-01T14:24:17.306926",
  "transactions": [
    {
      "date": "2025-09-01",
      "team": "Washington Nationals",
      "details": "Washington Nationalsactivated LHPAndrew Alvarez.",
      "player": "Andrew Alvarez"
    },
    {
      "date": "2025-09-01",
      "team": "Toronto Blue Jays",
      "details": "Toronto Blue Jaystransferred RHPNick Sandlinfrom the 15-day injured list to the 60-day injured list. Right elbow inflammation.",
      "player": "Nick Sandlin"
    },
    {
      "date": "2025-09-01",
      "team": "Toronto Blue Jays",
      "details": "Toronto Blue Jaysactivated SSIsiah Kiner-Falefa.",
      "player": "Isiah Kiner-Falefa"
    },
    {
      "date": "2025-09-01",
      "team": "Boston Red Sox",
      "details": "Boston Red Soxtransferred 3BMarcelo Mayerfrom the 10-day injured list to the 60-day injured list. Right wrist sprain.",
      "player": "Marcelo Mayer"
    },
    {
      "date": "2025-09-01",
      "team": "Minnesota Twins",
      "details": "Minnesota Twinsrecalled RHPTravis Adamsfrom St. Paul Saints.",
      "player": "Travis Adams"
    },
    {
      "date": "2025-09-01",
      "team": "Toronto Blue Jays",
      "details": "Toronto Blue Jaysselected the contract of RHPDillon Tatefrom Buffalo Bisons.",
      "player": "Dillon Tate"
    },
    {
      "date": "2025-09-01",
      "team": "Washington Nationals",
      "details": "Washington Nationalsselected the contract of LHPAndrew Alvarezfrom Rochester Red Wings.",
      "player": "Andrew Alvarez"
    },
    {
      "date": "2025-09-01",
      "team": "Cincinnati Reds",
      "details": "Cincinnati Redsrecalled RHPYosver Zuluetafrom Louisville Bats.",
      "player": "Yosver Zulueta"
    },
    {
      "date": "2025-09-01",
      "team": "New York Mets",
      "details": "New York Metsrecalled 2BLuisangel Acuñafrom Syracuse Mets.",
      "player": "Luisangel Acuña"
    },
    {
      "date": "2025-09-01",
      "team": "New York Mets",
      "details": "New York Metsrecalled RHPJustin Hagenmanfrom Syracuse Mets.",
      "player": "Justin Hagenman"
    },
    {
      "date": "2025-09-01",
      "team": "Minnesota Twins",
      "details": "Minnesota Twinsoptioned RHPMick Abelto St. Paul Saints.",
      "player": "Mick Abel"
    },
    {
      "date": "2025-09-01",
      "team": "Boston Red Sox",
      "details": "Boston Red Soxselected the contract of CAli Sánchezfrom Worcester Red Sox.",
      "player": "Ali Sánchez"
    },
    {
      "date": "2025-09-01",
      "team": "Minnesota Twins",
      "details": "Minnesota Twinsrecalled CFDaShawn Keirsey Jr.from St. Paul Saints.",
      "player": "DaShawn Keirsey Jr."
    },
    {
      "date": "2025-09-01",
      "team": "Washington Nationals",
      "details": "Washington Nationalsrecalled SSNasim Nuñezfrom Rochester Red Wings.",
      "player": "Nasim Nuñez"
    },
    {
      "date": "2025-09-01",
      "team": "Cincinnati Reds",
      "details": "Cincinnati Redsselected the contract of 3BSal Stewartfrom Louisville Bats.",
      "player": "Sal Stewart"
    },
    {
      "date": "2025-09-01",
      "team": "Minnesota Twins",
      "details": "Minnesota Twinsrecalled RHPNoah Davisfrom St. Paul Saints.",
      "player": "Noah Davis"
    },
    {
      "date": "2025-09-01",
      "team": "Boston Red Sox",
      "details": "Boston Red Soxrecalled RHPZack Kellyfrom Worcester Red Sox.",
      "player": "Zack Kelly"
    }
  ]
}