{
  "last_updated": "2026-04-16T15:02:01.437239",
  "transactions": [
    {
      "date": "2026-04-16",
      "team": "Unknown Team",
      "details": "RHPGarrett Whitlockchanged number to 22.",
      "player": "Garrett Whitlock"
    },
    {
      "date": "2026-04-16",
      "team": "Unknown Team",
      "details": "RHPRyan Watsonchanged number to 56.",
      "player": "Ryan Watson"
    },
    {
      "date": "2026-04-16",
      "team": "Unknown Team",
      "details": "SSTrevor Storychanged number to 10.",
      "player": "Trevor Story"
    },
    {
      "date": "2026-04-16",
      "team": "Unknown Team",
      "details": "RHPGreg Weissertchanged number to 57.",
      "player": "Greg Weissert"
    },
    {
      "date": "2026-04-16",
      "team": "Unknown Team",
      "details": "LHPRanger Suarezchanged number to 55.",
      "player": "Ranger Suarez"
    },
    {
      "date": "2026-04-16",
      "team": "Unknown Team",
      "details": "CCarlos Narváezchanged number to 75.",
      "player": "Carlos Narváez"
    },
    {
      "date": "2026-04-16",
      "team": "Unknown Team",
      "details": "CFCeddanne Rafaelachanged number to 3.",
      "player": "Ceddanne Rafaela"
    },
    {
      "date": "2026-04-16",
      "team": "Unknown Team",
      "details": "LHPJovani Moránchanged number to 47.",
      "player": "Jovani Morán"
    },
    {
      "date": "2026-04-16",
      "team": "Unknown Team",
      "details": "SSAndruw Monasteriochanged number to 32.",
      "player": "Andruw Monasterio"
    },
    {
      "date": "2026-04-16",
      "team": "Unknown Team",
      "details": "SSIsiah Kiner-Falefachanged number to 2.",
      "player": "Isiah Kiner-Falefa"
    },
    {
      "date": "2026-04-16",
      "team": "Unknown Team",
      "details": "RHPZack Kellychanged number to 76.",
      "player": "Zack Kelly"
    },
    {
      "date": "2026-04-16",
      "team": "Unknown Team",
      "details": "3BMarcelo Mayerchanged number to 11.",
      "player": "Marcelo Mayer"
    },
    {
      "date": "2026-04-16",
      "team": "Unknown Team",
      "details": "LHPConnelly Earlychanged number to 71.",
      "player": "Connelly Early"
    },
    {
      "date": "2026-04-16",
      "team": "Unknown Team",
      "details": "3BCaleb Durbinchanged number to 5.",
      "player": "Caleb Durbin"
    },
    {
      "date": "2026-04-16",
      "team": "Atlanta Braves",
      "details": "Atlanta Bravessent RHPSpencer Strideron a rehab assignment to Rome Emperors.",
      "player": "Spencer Strider"
    },
    {
      "date": "2026-04-16",
      "team": "Unknown Team",
      "details": "CFDrew Gilbertchanged number to 0.",
      "player": "Drew Gilbert"
    },
    {
      "date": "2026-04-16",
      "team": "Unknown Team",
      "details": "LHPKyle Backhuschanged number to 19.",
      "player": "Kyle Backhus"
    },
    {
      "date": "2026-04-16",
      "team": "Unknown Team",
      "details": "LHPJose A. Ferrerchanged number to 45.",
      "player": "Jose A. Ferrer"
    },
    {
      "date": "2026-04-16",
      "team": "Unknown Team",
      "details": "RHPKeaton Winnchanged number to 67.",
      "player": "Keaton Winn"
    },
    {
      "date": "2026-04-16",
      "team": "Unknown Team",
      "details": "RHPMatt Brashchanged number to 47.",
      "player": "Matt Brash"
    },
    {
      "date": "2026-04-16",
      "team": "Unknown Team",
      "details": "RHPEduard Bazardochanged number to 83.",
      "player": "Eduard Bazardo"
    },
    {
      "date": "2026-04-16",
      "team": "Unknown Team",
      "details": "LFRandy Arozarenachanged number to 56.",
      "player": "Randy Arozarena"
    },
    {
      "date": "2026-04-16",
      "team": "Unknown Team",
      "details": "RFDominic Canzonechanged number to 8.",
      "player": "Dominic Canzone"
    },
    {
      "date": "2026-04-16",
      "team": "Unknown Team",
      "details": "RHPLogan Webbchanged number to 62.",
      "player": "Logan Webb"
    },
    {
      "date": "2026-04-16",
      "team": "Unknown Team",
      "details": "RHPRyan Walkerchanged number to 74.",
      "player": "Ryan Walker"
    },
    {
      "date": "2026-04-16",
      "team": "Unknown Team",
      "details": "RHPBlade Tidwellchanged number to 46.",
      "player": "Blade Tidwell"
    },
    {
      "date": "2026-04-16",
      "team": "Unknown Team",
      "details": "RHPLanden Rouppchanged number to 65.",
      "player": "Landen Roupp"
    },
    {
      "date": "2026-04-16",
      "team": "Unknown Team",
      "details": "LHPRobbie Raychanged number to 38.",
      "player": "Robbie Ray"
    },
    {
      "date": "2026-04-16",
      "team": "Unknown Team",
      "details": "CDaniel Susacchanged number to 6.",
      "player": "Daniel Susac"
    },
    {
      "date": "2026-04-16",
      "team": "Unknown Team",
      "details": "LFHeliot Ramoschanged number to 17.",
      "player": "Heliot Ramos"
    },
    {
      "date": "2026-04-16",
      "team": "Unknown Team",
      "details": "3BCasey Schmittchanged number to 10.",
      "player": "Casey Schmitt"
    },
    {
      "date": "2026-04-16",
      "team": "Unknown Team",
      "details": "CFJung Hoo Leechanged number to 51.",
      "player": "Jung Hoo Lee"
    },
    {
      "date": "2026-04-16",
      "team": "Unknown Team",
      "details": "RHPTyler Mahlechanged number to 54.",
      "player": "Tyler Mahle"
    },
    {
      "date": "2026-04-16",
      "team": "Unknown Team",
      "details": "LHPErik Millerchanged number to 68.",
      "player": "Erik Miller"
    },
    {
      "date": "2026-04-16",
      "team": "Unknown Team",
      "details": "2BChristian Kosschanged number to 50.",
      "player": "Christian Koss"
    },
    {
      "date": "2026-04-16",
      "team": "Unknown Team",
      "details": "RHPAdrian Houserchanged number to 12.",
      "player": "Adrian Houser"
    },
    {
      "date": "2026-04-16",
      "team": "Unknown Team",
      "details": "RHPCaleb Kilianchanged number to 45.",
      "player": "Caleb Kilian"
    },
    {
      "date": "2026-04-16",
      "team": "Unknown Team",
      "details": "RFJerar Encarnacionchanged number to 19.",
      "player": "Jerar Encarnacion"
    },
    {
      "date": "2026-04-16",
      "team": "Unknown Team",
      "details": "LHPTanner Scottchanged number to 66.",
      "player": "Tanner Scott"
    },
    {
      "date": "2026-04-16",
      "team": "Unknown Team",
      "details": "RHPEmmet Sheehanchanged number to 80.",
      "player": "Emmet Sheehan"
    },
    {
      "date": "2026-04-16",
      "team": "Unknown Team",
      "details": "2BMiguel Rojaschanged number to 72.",
      "player": "Miguel Rojas"
    },
    {
      "date": "2026-04-16",
      "team": "Unknown Team",
      "details": "CDalton Rushingchanged number to 68.",
      "player": "Dalton Rushing"
    },
    {
      "date": "2026-04-16",
      "team": "Unknown Team",
      "details": "CFAndy Pageschanged number to 44.",
      "player": "Andy Pages"
    },
    {
      "date": "2026-04-16",
      "team": "Unknown Team",
      "details": "RHPWill Kleinchanged number to 61.",
      "player": "Will Klein"
    },
    {
      "date": "2026-04-16",
      "team": "Unknown Team",
      "details": "3BMax Muncychanged number to 13.",
      "player": "Max Muncy"
    },
    {
      "date": "2026-04-16",
      "team": "Unknown Team",
      "details": "2BHyeseong Kimchanged number to 6.",
      "player": "Hyeseong Kim"
    },
    {
      "date": "2026-04-16",
      "team": "Unknown Team",
      "details": "TWPShohei Ohtanichanged number to 17.",
      "player": "Shohei Ohtani"
    },
    {
      "date": "2026-04-16",
      "team": "Unknown Team",
      "details": "RFTeoscar Hernándezchanged number to 37.",
      "player": "Teoscar Hernández"
    },
    {
      "date": "2026-04-16",
      "team": "Unknown Team",
      "details": "RHPKyle Hurtchanged number to 63.",
      "player": "Kyle Hurt"
    },
    {
      "date": "2026-04-16",
      "team": "Unknown Team",
      "details": "RHPTyler Glasnowchanged number to 31.",
      "player": "Tyler Glasnow"
    }
  ]
}