{
  "last_updated": "2026-01-28T22:35:31.235482",
  "transactions": [
    {
      "date": "2026-01-28",
      "team": "Athletics",
      "details": "Athleticsinvited non-roster RHPKade Morristo spring training.",
      "player": "Kade Morris"
    },
    {
      "date": "2026-01-28",
      "team": "Athletics",
      "details": "Athleticsinvited non-roster SSLeo De Vriesto spring training.",
      "player": "Leo De Vries"
    },
    {
      "date": "2026-01-28",
      "team": "Athletics",
      "details": "Athleticsinvited non-roster LFClark Elliottto spring training.",
      "player": "Clark Elliott"
    },
    {
      "date": "2026-01-28",
      "team": "Athletics",
      "details": "Athleticsinvited non-roster RHPGustavo Rodriguezto spring training.",
      "player": "Gustavo Rodriguez"
    },
    {
      "date": "2026-01-28",
      "team": "Athletics",
      "details": "Athleticsinvited non-roster CFRyan Laskoto spring training.",
      "player": "Ryan Lasko"
    },
    {
      "date": "2026-01-28",
      "team": "Athletics",
      "details": "Athleticsinvited non-roster 3BTommy Whiteto spring training.",
      "player": "Tommy White"
    },
    {
      "date": "2026-01-28",
      "team": "Athletics",
      "details": "Athleticsinvited non-roster 2BMichael Stefanicto spring training.",
      "player": "Michael Stefanic"
    },
    {
      "date": "2026-01-28",
      "team": "Athletics",
      "details": "Athleticsinvited non-roster RHPWander Sueroto spring training.",
      "player": "Wander Suero"
    },
    {
      "date": "2026-01-28",
      "team": "Athletics",
      "details": "Athleticsinvited non-roster 1BJoey Menesesto spring training.",
      "player": "Joey Meneses"
    },
    {
      "date": "2026-01-28",
      "team": "Athletics",
      "details": "Athleticsinvited non-roster RHPBrooks Krisketo spring training.",
      "player": "Brooks Kriske"
    },
    {
      "date": "2026-01-28",
      "team": "Athletics",
      "details": "Athleticsinvited non-roster OFCade Marloweto spring training.",
      "player": "Cade Marlowe"
    },
    {
      "date": "2026-01-28",
      "team": "Athletics",
      "details": "Athleticsinvited non-roster 3BEuribiel Angelesto spring training.",
      "player": "Euribiel Angeles"
    },
    {
      "date": "2026-01-28",
      "team": "Washington Nationals",
      "details": "Washington Nationalsdesignated LHPKonnor Pilkingtonfor assignment.",
      "player": "Konnor Pilkington"
    },
    {
      "date": "2026-01-28",
      "team": "Colorado Rockies",
      "details": "Colorado Rockiesdesignated RFYanquiel Fernándezfor assignment.",
      "player": "Yanquiel Fernández"
    },
    {
      "date": "2026-01-28",
      "team": "Athletics",
      "details": "Athleticsinvited non-roster RHPYunior Turto spring training.",
      "player": "Yunior Tur"
    },
    {
      "date": "2026-01-28",
      "team": "Athletics",
      "details": "Athleticsinvited non-roster RHPJJ Gossto spring training.",
      "player": "JJ Goss"
    },
    {
      "date": "2026-01-28",
      "team": "Cincinnati Reds",
      "details": "Cincinnati Redssigned free agent RHPDarren McCaughanto a minor league contract and invited him to spring training.",
      "player": "Darren McCaughan"
    },
    {
      "date": "2026-01-28",
      "team": "Atlanta Braves",
      "details": "Atlanta Bravesinvited non-roster LHPJamie Arnoldto spring training.",
      "player": "Jamie Arnold"
    },
    {
      "date": "2026-01-28",
      "team": "Athletics",
      "details": "Athleticsinvited non-roster RFHenry Bolteto spring training.",
      "player": "Henry Bolte"
    },
    {
      "date": "2026-01-28",
      "team": "Athletics",
      "details": "Athleticsinvited non-roster CShane McGuireto spring training.",
      "player": "Shane McGuire"
    },
    {
      "date": "2026-01-28",
      "team": "Athletics",
      "details": "Athleticsinvited non-roster CBryan Lavastidato spring training.",
      "player": "Bryan Lavastida"
    },
    {
      "date": "2026-01-28",
      "team": "Athletics",
      "details": "Athleticsinvited non-roster RHPKenya Hugginsto spring training.",
      "player": "Kenya Huggins"
    },
    {
      "date": "2026-01-28",
      "team": "Athletics",
      "details": "Athleticsinvited non-roster LHPMatt Krookto spring training.",
      "player": "Matt Krook"
    },
    {
      "date": "2026-01-28",
      "team": "Athletics",
      "details": "Athleticsinvited non-roster CChad Wallachto spring training.",
      "player": "Chad Wallach"
    },
    {
      "date": "2026-01-28",
      "team": "Athletics",
      "details": "Athleticsinvited non-roster LHPWei-En Linto spring training.",
      "player": "Wei-En Lin"
    },
    {
      "date": "2026-01-28",
      "team": "Athletics",
      "details": "Athleticsinvited non-roster LHPGage Jumpto spring training.",
      "player": "Gage Jump"
    },
    {
      "date": "2026-01-28",
      "team": "Athletics",
      "details": "Athleticsinvited non-roster SSJoshua Kuroda-Grauerto spring training.",
      "player": "Joshua Kuroda-Grauer"
    },
    {
      "date": "2026-01-28",
      "team": "Athletics",
      "details": "Athleticsinvited non-roster RHPGeoff Hartliebto spring training.",
      "player": "Geoff Hartlieb"
    },
    {
      "date": "2026-01-28",
      "team": "Athletics",
      "details": "Athleticsinvited non-roster CBrian Servento spring training.",
      "player": "Brian Serven"
    },
    {
      "date": "2026-01-28",
      "team": "Athletics",
      "details": "Athleticsinvited non-roster RHPNick Hernandezto spring training.",
      "player": "Nick Hernandez"
    },
    {
      "date": "2026-01-28",
      "team": "Athletics",
      "details": "Athleticsinvited non-roster RHPNick Andersonto spring training.",
      "player": "Nick Anderson"
    },
    {
      "date": "2026-01-28",
      "team": "Athletics",
      "details": "Athleticsinvited non-roster RHPJoel Kuhnelto spring training.",
      "player": "Joel Kuhnel"
    },
    {
      "date": "2026-01-28",
      "team": "Athletics",
      "details": "Athleticsinvited non-roster LHPDomingo Roblesto spring training.",
      "player": "Domingo Robles"
    },
    {
      "date": "2026-01-28",
      "team": "Los Angeles Angels",
      "details": "Los Angeles Angelsclaimed RHPKaleb Ortoff waivers fromNew York Yankees.",
      "player": "Kaleb Ort"
    },
    {
      "date": "2026-01-28",
      "team": "Minnesota Twins",
      "details": "Minnesota Twinstraded 2B Edouard Julien and RHPPierson OhltoColorado Rockiesfor RHP Jace Kaminska and cash.",
      "player": "Pierson Ohl"
    },
    {
      "date": "2026-01-28",
      "team": "Washington Nationals",
      "details": "Washington Nationalsclaimed SSTsung-Che Chengoff waivers fromNew York Mets.",
      "player": "Tsung-Che Cheng"
    },
    {
      "date": "2026-01-28",
      "team": "Colorado Rockies",
      "details": "Colorado Rockiestraded RHPAngel ChivillitoNew York Yankeesfor 1B T.J. Rumfield.",
      "player": "Angel Chivilli"
    },
    {
      "date": "2026-01-28",
      "team": "Colorado Rockies",
      "details": "Colorado Rockiestraded RHP Angel Chivilli toNew York Yankeesfor 1BT.J. Rumfield.",
      "player": "T.J. Rumfield"
    },
    {
      "date": "2026-01-28",
      "team": "Minnesota Twins",
      "details": "Minnesota Twinstraded 2B Edouard Julien and RHP Pierson Ohl toColorado Rockiesfor RHPJace Kaminskaand cash.",
      "player": "Jace Kaminska"
    },
    {
      "date": "2026-01-28",
      "team": "Minnesota Twins",
      "details": "Minnesota Twinstraded 2BEdouard Julienand RHP Pierson Ohl toColorado Rockiesfor RHP Jace Kaminska and cash.",
      "player": "Edouard Julien"
    }
  ]
}