{
  "last_updated": "2025-06-17T20:28:22.453488",
  "transactions": [
    {
      "date": "2025-06-17",
      "team": "Boston Red Sox",
      "details": "Boston Red Soxsent RFWilyer Abreuon a rehab assignment to Worcester Red Sox.",
      "player": "Wilyer Abreu"
    },
    {
      "date": "2025-06-17",
      "team": "San Diego Padres",
      "details": "San Diego Padressigned free agent CGabriel Teranto a minor league contract.",
      "player": "Gabriel Teran"
    },
    {
      "date": "2025-06-17",
      "team": "Cincinnati Reds",
      "details": "Cincinnati Redsplaced RHPGraham Ashcrafton the 15-day injured list retroactive to June 16, 2025. Right groin strain.",
      "player": "Graham Ashcraft"
    },
    {
      "date": "2025-06-17",
      "team": "Milwaukee Brewers",
      "details": "Milwaukee Brewerssent CFGarrett Mitchellon a rehab assignment to Nashville Sounds.",
      "player": "Garrett Mitchell"
    },
    {
      "date": "2025-06-17",
      "team": "Toronto Blue Jays",
      "details": "Toronto Blue Jaysdesignated RHPErik Swansonfor assignment.",
      "player": "Erik Swanson"
    },
    {
      "date": "2025-06-17",
      "team": "Toronto Blue Jays",
      "details": "Toronto Blue Jaysplaced RHPBowden Francison the 15-day injured list retroactive to June 15, 2025. Right shoulder impingement.",
      "player": "Bowden Francis"
    },
    {
      "date": "2025-06-17",
      "team": "New York Mets",
      "details": "New York Metssent LHPBrooks Raleyon a rehab assignment to St. Lucie Mets.",
      "player": "Brooks Raley"
    },
    {
      "date": "2025-06-17",
      "team": "Cleveland Guardians",
      "details": "Cleveland Guardianssent RHPTrevor Stephanon a rehab assignment to Columbus Clippers.",
      "player": "Trevor Stephan"
    },
    {
      "date": "2025-06-17",
      "team": "Toronto Blue Jays",
      "details": "Toronto Blue Jayssent RHPRyan Burron a rehab assignment to Dunedin Blue Jays.",
      "player": "Ryan Burr"
    },
    {
      "date": "2025-06-17",
      "team": "Detroit Tigers",
      "details": "Detroit Tigerssent RHPAlex Langeon a rehab assignment to West Michigan Whitecaps.",
      "player": "Alex Lange"
    },
    {
      "date": "2025-06-17",
      "team": "Philadelphia Phillies",
      "details": "Philadelphia Philliessigned free agent SSJonathan Alcantarato a minor league contract.",
      "player": "Jonathan Alcantara"
    },
    {
      "date": "2025-06-17",
      "team": "Pittsburgh Pirates",
      "details": "Pittsburgh Piratessigned free agent RHPJack Nobleto a minor league contract.",
      "player": "Jack Noble"
    },
    {
      "date": "2025-06-17",
      "team": "New York Mets",
      "details": "New York Metssent 3BMark Vientoson a rehab assignment to Syracuse Mets.",
      "player": "Mark Vientos"
    },
    {
      "date": "2025-06-17",
      "team": "New York Mets",
      "details": "New York Metsplaced RHPTylor Megillon the 15-day injured list retroactive to June 15, 2025. Right elbow sprain.",
      "player": "Tylor Megill"
    },
    {
      "date": "2025-06-17",
      "team": "Chicago White Sox",
      "details": "Chicago White Soxactivated 2BLenyn Sosafrom the 10-day injured list.",
      "player": "Lenyn Sosa"
    },
    {
      "date": "2025-06-17",
      "team": "Cleveland Guardians",
      "details": "Cleveland Guardianssigned free agent RHPDwayne Matosto a minor league contract.",
      "player": "Dwayne Matos"
    },
    {
      "date": "2025-06-17",
      "team": "Chicago White Sox",
      "details": "Chicago White Soxsent LHPFraser Ellardon a rehab assignment to Charlotte Knights.",
      "player": "Fraser Ellard"
    },
    {
      "date": "2025-06-17",
      "team": "Seattle Mariners",
      "details": "Seattle Marinersclaimed LFJacob Hurtubiseoff waivers fromCincinnati Reds.",
      "player": "Jacob Hurtubise"
    },
    {
      "date": "2025-06-17",
      "team": "New York Mets",
      "details": "New York Metsrecalled RHPJustin Garzafrom Syracuse Mets.",
      "player": "Justin Garza"
    },
    {
      "date": "2025-06-17",
      "team": "Chicago White Sox",
      "details": "Chicago White Soxoptioned LFBrooks Baldwinto Charlotte Knights.",
      "player": "Brooks Baldwin"
    },
    {
      "date": "2025-06-17",
      "team": "Toronto Blue Jays",
      "details": "Toronto Blue Jaysrecalled RHPPaxton Schultzfrom Buffalo Bisons.",
      "player": "Paxton Schultz"
    },
    {
      "date": "2025-06-17",
      "team": "Toronto Blue Jays",
      "details": "Toronto Blue Jaysselected the contract of LHPJustin Bruihlfrom Buffalo Bisons.",
      "player": "Justin Bruihl"
    },
    {
      "date": "2025-06-17",
      "team": "Baltimore Orioles",
      "details": "Baltimore Oriolesrecalled LHPGrant Wolframfrom Norfolk Tides.",
      "player": "Grant Wolfram"
    },
    {
      "date": "2025-06-17",
      "team": "Baltimore Orioles",
      "details": "Baltimore Oriolesoptioned RHPColin Selbyto Norfolk Tides.",
      "player": "Colin Selby"
    },
    {
      "date": "2025-06-17",
      "team": "Cincinnati Reds",
      "details": "Cincinnati Redsrecalled RHPLuis Meyfrom Louisville Bats.",
      "player": "Luis Mey"
    }
  ]
}