{
  "last_updated": "2026-04-11T15:40:36.159305",
  "transactions": [
    {
      "date": "2026-04-11",
      "team": "Minnesota Twins",
      "details": "Minnesota Twinsplaced 3BRoyce Lewison the 10-day injured list retroactive to April 10, 2025. Left knee sprain.",
      "player": "Royce Lewis"
    },
    {
      "date": "2026-04-11",
      "team": "Minnesota Twins",
      "details": "Minnesota Twinsplaced RHPCody Lawerysonon the 15-day injured list retroactive to April 9, 2026. Right forearm strain.",
      "player": "Cody Laweryson"
    },
    {
      "date": "2026-04-11",
      "team": "Minnesota Twins",
      "details": "Minnesota Twinsrecalled RHPAndrew Morrisfrom St. Paul Saints.",
      "player": "Andrew Morris"
    },
    {
      "date": "2026-04-11",
      "team": "Minnesota Twins",
      "details": "Minnesota Twinsrecalled CFRyan Kreidlerfrom St. Paul Saints.",
      "player": "Ryan Kreidler"
    }
  ]
}