{
  "last_updated": "2026-04-11T18:57:42.129494",
  "transactions": [
    {
      "date": "2026-04-11",
      "team": "Los Angeles Angels",
      "details": "Los Angeles Angelsdesignated 3BJeimer Candelariofor assignment.",
      "player": "Jeimer Candelario"
    },
    {
      "date": "2026-04-11",
      "team": "New York Mets",
      "details": "New York Metsdesignated LHPRichard Loveladyfor assignment.",
      "player": "Richard Lovelady"
    },
    {
      "date": "2026-04-11",
      "team": "Los Angeles Angels",
      "details": "Los Angeles Angelsactivated 2BVaughn Grissomfrom the 10-day injured list.",
      "player": "Vaughn Grissom"
    },
    {
      "date": "2026-04-11",
      "team": "Minnesota Twins",
      "details": "Minnesota Twinsplaced 3BRoyce Lewison the 10-day injured list retroactive to April 10, 2025. Left knee sprain.",
      "player": "Royce Lewis"
    },
    {
      "date": "2026-04-11",
      "team": "Detroit Tigers",
      "details": "Detroit Tigerssigned free agent OFTyler Gentryto a minor league contract.",
      "player": "Tyler Gentry"
    },
    {
      "date": "2026-04-11",
      "team": "Minnesota Twins",
      "details": "Minnesota Twinsplaced RHPCody Lawerysonon the 15-day injured list retroactive to April 9, 2026. Right forearm strain.",
      "player": "Cody Laweryson"
    },
    {
      "date": "2026-04-11",
      "team": "Minnesota Twins",
      "details": "Minnesota Twinsrecalled CFRyan Kreidlerfrom St. Paul Saints.",
      "player": "Ryan Kreidler"
    },
    {
      "date": "2026-04-11",
      "team": "Minnesota Twins",
      "details": "Minnesota Twinsrecalled RHPAndrew Morrisfrom St. Paul Saints.",
      "player": "Andrew Morris"
    },
    {
      "date": "2026-04-11",
      "team": "New York Mets",
      "details": "New York Metsselected the contract of RHPCraig Kimbrelfrom St. Lucie Mets.",
      "player": "Craig Kimbrel"
    }
  ]
}