{
  "last_updated": "2025-07-11T18:37:05.133920",
  "transactions": [
    {
      "date": "2025-07-11",
      "team": "Houston Astros",
      "details": "Houston Astrosselected the contract of SSBrice Matthewsfrom Sugar Land Space Cowboys.",
      "player": "Brice Matthews"
    },
    {
      "date": "2025-07-11",
      "team": "Cleveland Guardians",
      "details": "Cleveland Guardiansrecalled RHPNic Enrightfrom Columbus Clippers.",
      "player": "Nic Enright"
    },
    {
      "date": "2025-07-11",
      "team": "New York Mets",
      "details": "New York Metsoptioned RHPAustin Warrento Syracuse Mets.",
      "player": "Austin Warren"
    },
    {
      "date": "2025-07-11",
      "team": "Chicago White Sox",
      "details": "Chicago White Soxrecalled LHPFraser Ellardfrom Charlotte Knights.",
      "player": "Fraser Ellard"
    },
    {
      "date": "2025-07-11",
      "team": "Baltimore Orioles",
      "details": "Baltimore Oriolesoptioned LHPGrant Wolframto Norfolk Tides.",
      "player": "Grant Wolfram"
    }
  ]
}